odoo/addons/product_contract/README.rst
odoo/addons/product_contract/__init__.py
odoo/addons/product_contract/__manifest__.py
odoo/addons/product_contract/i18n/de.po
odoo/addons/product_contract/i18n/es.po
odoo/addons/product_contract/i18n/fi.po
odoo/addons/product_contract/i18n/fr.po
odoo/addons/product_contract/i18n/hi_IN.po
odoo/addons/product_contract/i18n/hr.po
odoo/addons/product_contract/i18n/hr_HR.po
odoo/addons/product_contract/i18n/it.po
odoo/addons/product_contract/i18n/nl.po
odoo/addons/product_contract/i18n/nl_NL.po
odoo/addons/product_contract/i18n/product_contract.pot
odoo/addons/product_contract/i18n/pt.po
odoo/addons/product_contract/i18n/pt_BR.po
odoo/addons/product_contract/i18n/ru.po
odoo/addons/product_contract/i18n/sv.po
odoo/addons/product_contract/i18n/tr.po
odoo/addons/product_contract/i18n/tr_TR.po
odoo/addons/product_contract/migrations/18.0.1.0.0/post-migration.py
odoo/addons/product_contract/migrations/18.0.1.0.0/pre-migrate.py
odoo/addons/product_contract/models/__init__.py
odoo/addons/product_contract/models/contract.py
odoo/addons/product_contract/models/contract_line.py
odoo/addons/product_contract/models/product_template.py
odoo/addons/product_contract/models/res_company.py
odoo/addons/product_contract/models/res_config_settings.py
odoo/addons/product_contract/models/sale_order.py
odoo/addons/product_contract/models/sale_order_line.py
odoo/addons/product_contract/models/sale_order_line_contract_mixin.py
odoo/addons/product_contract/readme/CONTRIBUTORS.md
odoo/addons/product_contract/readme/DESCRIPTION.md
odoo/addons/product_contract/readme/ROADMAP.md
odoo/addons/product_contract/readme/USAGE.md
odoo/addons/product_contract/security/ir.model.access.csv
odoo/addons/product_contract/static/description/icon.png
odoo/addons/product_contract/static/description/index.html
odoo/addons/product_contract/static/src/js/contract_configurator_controller.esm.js
odoo/addons/product_contract/static/src/js/sale_product_field.esm.js
odoo_addon_product_contract-18.0.1.1.2.3.dist-info/METADATA
odoo_addon_product_contract-18.0.1.1.2.3.dist-info/WHEEL
odoo_addon_product_contract-18.0.1.1.2.3.dist-info/top_level.txt
odoo_addon_product_contract-18.0.1.1.2.3.dist-info/RECORD
