Metadata-Version: 2.1
Name: odoo-addon-product_contract
Version: 18.0.1.1.2.3
Requires-Python: >=3.10
Requires-Dist: odoo-addon-contract_termination==18.0.*
Requires-Dist: odoo==18.0.*
Requires-Dist: python-dateutil
Summary: Recurring - Product Contract
Home-page: https://github.com/OCA/contract
License: AGPL-3
Author: LasLabs, ACSONE SA/NV, Odoo Community Association (OCA)
Author-email: support@odoo-community.org
Classifier: Programming Language :: Python
Classifier: Framework :: Odoo
Classifier: Framework :: Odoo :: 18.0
Classifier: License :: OSI Approved :: GNU Affero General Public License v3
